Workbook

Sheet README
A2: Lumina Retail Co. — Sales & Financial Analysis Model
A3: Built in Excel | Formulas, Pivot-style Summaries, Dashboard & 12-Month Forecast
B5: Purpose
B6: This workbook analyzes two years of multi-region retail sales data, builds a SUMIFS-driven monthly summary, projects a 12-month income statement from a driver-based assumptions panel, and visualizes results on an executive dashboard.
B8: How it's built
B9: Every figure that can be calculated IS calculated with a live formula — nothing is hardcoded. Change any blue input cell and the model, summary, and charts recalculate automatically.
B11: Sheet Guide
B12: Sheet | C12: What's in it
B13: Dashboard | C13: Executive KPI summary and charts — start here.
B14: Lookup Reference | C14: Category rate card; demonstrates XLOOKUP, VLOOKUP, and INDEX/MATCH side by side.
B15: Assumptions | C15: Blue-highlighted driver inputs for the 12-month forecast (growth, margin, opex, tax).
B16: Sales Data | C16: 1,728-row raw transaction table: 24 months x 4 regions x 3 categories x weekly grain.
B17: Monthly Summary | C17: SUMIFS pivot-style rollup of raw data by month, with margin % and YoY growth.
B18: Financial Model | C18: 12-month forward income statement driven entirely by the Assumptions sheet.
B20: Color legend:
B21: Blue text | C21: Hardcoded input / editable assumption
B22: Black text | C22: Formula or calculation
B23: Green text | C23: Link pulling from another sheet

Sheet Dashboard
A1: Lumina Retail Co. — Executive Dashboard
A2: FY2024–FY2025 Actuals | FY2026 Forecast
A4: FY2025 Revenue | C4: FY2025 Gross Margin | E4: FY2025 Revenue YoY | G4: FY2026 Forecast Revenue | I4: FY2026 Forecast Net Income | K4: FY2026 Forecast Net Margin
A5: =SUMPRODUCT((RIGHT('Monthly Summary'!A4:A27,4)="2025")*'Monthly Summary'!C4:C27) -> 2.7696579e+08 | C5: =SUMPRODUCT((RIGHT('Monthly Summary'!A4:A27,4)="2025")*'Monthly Summary'!E4:E27)/SUMPRODUCT((RIGHT('Monthly Summary'!A4:A27,4)="2025")*'Monthly Summary'!C4:C27) -> 0.53068118 | E5: ='Monthly Summary'!G27 -> 0.15960593 | G5: ='Financial Model'!N4 -> 4.8790665e+08 | I5: ='Financial Model'!N15 -> 83880539 | K5: ='Financial Model'!N15/'Financial Model'!N4 -> 0.17191924
A8: Chart source data pulls live from 'Monthly Summary' and 'Financial Model' sheets.

Sheet Lookup Reference
A1: Lookup Reference — Category Rate Card
A2: Feeds Sales Data via XLOOKUP; also compares XLOOKUP, VLOOKUP, and INDEX/MATCH side by side
A3: Category | B3: Base Unit Price (₹) | C3: COGS Rate | D3: Target Gross Margin %
A4: Apparel | B4: 4011 | C4: 0.46 | D4: =1-C4 -> 0.54
A5: Footwear | B5: 6494 | C5: 0.52 | D5: =1-C5 -> 0.48
A6: Accessories | B6: 2292 | C6: 0.38 | D6: =1-C6 -> 0.62
A9: Lookup Function Comparison
A10: Search Category: | B10: Footwear
A12: Function | B12: Result (COGS Rate) | C12: Notes
A13: XLOOKUP | B13: =IFERROR(xlookup(B10,'Lookup Reference'!$A$4:$A$6,'Lookup Reference'!$C$4:$C$6),INDEX('Lookup Reference'!$C$4:$C$6,MATCH(B10,'Lookup Reference'!$A$4:$A$6,0))) -> 0.52 | C13: Modern exact-match lookup; returns COGS Rate for the searched category
A14: VLOOKUP | B14: =VLOOKUP(B10,'Lookup Reference'!$A$4:$C$6,3,FALSE()) -> 0.52 | C14: Classic lookup; column index 3 = COGS Rate, exact match
A15: INDEX/MATCH | B15: =INDEX('Lookup Reference'!$C$4:$C$6,MATCH(B10,'Lookup Reference'!$A$4:$A$6,0)) -> 0.52 | C15: Position-based lookup; flexible if columns get reordered
A17: All three match: | B17: =IF(AND(B13=B14,B14=B15),"TRUE","CHECK") -> TRUE
A19: Note: the XLOOKUP formula is wrapped in IFERROR with an INDEX/MATCH fallback so the workbook still calculates on Excel 2016/2019 or older LibreOffice, which predate XLOOKUP. On Excel 2021/365 the XLOOKUP branch runs directly.

Sheet Sales Data
A1: Raw Sales Data — 24 Months x 4 Regions x 3 Categories
A3: Date | B3: Month | C3: Region | D3: Category | E3: Units Sold | F3: Unit Price (₹) | G3: Revenue (₹) | H3: COGS Rate | I3: COGS (₹) | J3: Gross Profit (₹)
A4: 45292 | B4: Jan-2024 | C4: North | D4: Apparel | E4: 398 | F4: 3898.31 | G4: =E4*F4 -> 1551527.4 | H4: =IFERROR(xlookup(D4,'Lookup Reference'!$A$4:$A$6,'Lookup Reference'!$C$4:$C$6),INDEX('Lookup Reference'!$C$4:$C$6,MATCH(D4,'Lookup Reference'!$A$4:$A$6,0))) -> 0.46 | I4: =G4*H4 -> 713702.59 | J4: =G4-I4 -> 837824.79
A5: 45292 | B5: Jan-2024 | C5: North | D5: Footwear | E5: 226 | F5: 6414.74 | G5: =E5*F5 -> 1449731.2 | H5: =IFERROR(xlookup(D5,'Lookup Reference'!$A$4:$A$6,'Lookup Reference'!$C$4:$C$6),INDEX('Lookup Reference'!$C$4:$C$6,MATCH(D5,'Lookup Reference'!$A$4:$A$6,0))) -> 0.52 | I5: =G5*H5 -> 753860.24 | J5: =G5-I5 -> 695871
A6: 45292 | B6: Jan-2024 | C6: North | D6: Accessories | E6: 330 | F6: 2347.39 | G6: =E6*F6 -> 774638.7 | H6: =IFERROR(xlookup(D6,'Lookup Reference'!$A$4:$A$6,'Lookup Reference'!$C$4:$C$6),INDEX('Lookup Reference'!$C$4:$C$6,MATCH(D6,'Lookup Reference'!$A$4:$A$6,0))) -> 0.38 | I6: =G6*H6 -> 294362.71 | J6: =G6-I6 -> 480275.99
A7: 45292 | B7: Jan-2024 | C7: South | D7: Apparel | E7: 371 | F7: 3918.37 | G7: =E7*F7 -> 1453715.3 | H7: =IFERROR(xlookup(D7,'Lookup Reference'!$A$4:$A$6,'Lookup Reference'!$C$4:$C$6),INDEX('Lookup Reference'!$C$4:$C$6,MATCH(D7,'Lookup Reference'!$A$4:$A$6,0))) -> 0.46 | I7: =G7*H7 -> 668709.02 | J7: =G7-I7 -> 785006.25
A8: 45292 | B8: Jan-2024 | C8: South | D8: Footwear | E8: 206 | F8: 6314.46 | G8: =E8*F8 -> 1300778.8 | H8: =IFERROR(xlookup(D8,'Lookup Reference'!$A$4:$A$6,'Lookup Reference'!$C$4:$C$6),INDEX('Lookup Reference'!$C$4:$C$6,MATCH(D8,'Lookup Reference'!$A$4:$A$6,0))) -> 0.52 | I8: =G8*H8 -> 676404.96 | J8: =G8-I8 -> 624373.8
A9: 45292 | B9: Jan-2024 | C9: South | D9: Accessories | E9: 256 | F9: 2315.88 | G9: =E9*F9 -> 592865.28 | H9: =IFERROR(xlookup(D9,'Lookup Reference'!$A$4:$A$6,'Lookup Reference'!$C$4:$C$6),INDEX('Lookup Reference'!$C$4:$C$6,MATCH(D9,'Lookup Reference'!$A$4:$A$6,0))) -> 0.38 | I9: =G9*H9 -> 225288.81 | J9: =G9-I9 -> 367576.47
A10: 45292 | B10: Jan-2024 | C10: East | D10: Apparel | E10: 364 | F10: 3954.65 | G10: =E10*F10 -> 1439492.6 | H10: =IFERROR(xlookup(D10,'Lookup Reference'!$A$4:$A$6,'Lookup Reference'!$C$4:$C$6),INDEX('Lookup Reference'!$C$4:$C$6,MATCH(D10,'Lookup Reference'!$A$4:$A$6,0))) -> 0.46 | I10: =G10*H10 -> 662166.6 | J10: =G10-I10 -> 777326
A11: 45292 | B11: Jan-2024 | C11: East | D11: Footwear | E11: 263 | F11: 6581.86 | G11: =E11*F11 -> 1731029.2 | H11: =IFERROR(xlookup(D11,'Lookup Reference'!$A$4:$A$6,'Lookup Reference'!$C$4:$C$6),INDEX('Lookup Reference'!$C$4:$C$6,MATCH(D11,'Lookup Reference'!$A$4:$A$6,0))) -> 0.52 | I11: =G11*H11 -> 900135.17 | J11: =G11-I11 -> 830894.01
A12: 45292 | B12: Jan-2024 | C12: East | D12: Accessories | E12: 310 | F12: 2331.16 | G12: =E12*F12 -> 722659.6 | H12: =IFERROR(xlookup(D12,'Lookup Reference'!$A$4:$A$6,'Lookup Reference'!$C$4:$C$6),INDEX('Lookup Reference'!$C$4:$C$6,MATCH(D12,'Lookup Reference'!$A$4:$A$6,0))) -> 0.38 | I12: =G12*H12 -> 274610.65 | J12: =G12-I12 -> 448048.95
A13: 45292 | B13: Jan-2024 | C13: West | D13: Apparel | E13: 384 | F13: 3892.58 | G13: =E13*F13 -> 1494750.7 | H13: =IFERROR(xlookup(D13,'Lookup Reference'!$A$4:$A$6,'Lookup Reference'!$C$4:$C$6),INDEX('Lookup Reference'!$C$4:$C$6,MATCH(D13,'Lookup Reference'!$A$4:$A$6,0))) -> 0.46 | I13: =G13*H13 -> 687585.33 | J13: =G13-I13 -> 807165.39
A14: 45292 | B14: Jan-2024 | C14: West | D14: Footwear | E14: 237 | F14: 6662.08 | G14: =E14*F14 -> 1578913 | H14: =IFERROR(xlookup(D14,'Lookup Reference'!$A$4:$A$6,'Lookup Reference'!$C$4:$C$6),INDEX('Lookup Reference'!$C$4:$C$6,MATCH(D14,'Lookup Reference'!$A$4:$A$6,0))) -> 0.52 | I14: =G14*H14 -> 821034.74 | J14: =G14-I14 -> 757878.22
A15: 45292 | B15: Jan-2024 | C15: West | D15: Accessories | E15: 278 | F15: 2251.89 | G15: =E15*F15 -> 626025.42 | H15: =IFERROR(xlookup(D15,'Lookup Reference'!$A$4:$A$6,'Lookup Reference'!$C$4:$C$6),INDEX('Lookup Reference'!$C$4:$C$6,MATCH(D15,'Lookup Reference'!$A$4:$A$6,0))) -> 0.38 | I15: =G15*H15 -> 237889.66 | J15: =G15-I15 -> 388135.76
... A291: 45992 | B291: Dec-2025 | C291: West | D291: Accessories | E291: 613 | F291: 2371.26 | G291: =E291*F291 -> 1453582.4 | H291: =IFERROR(xlookup(D291,'Lookup Reference'!$A$4:$A$6,'Lookup Reference'!$C$4:$C$6),INDEX('Lookup Reference'!$C$4:$C$6,MATCH(D291,'Lookup Reference'!$A$4:$A$6,0))) -> 0.38 | I291: =G291*H291 -> 552361.3 | J291: =G291-I291 -> 901221.08

Sheet Monthly Summary
A1: Monthly Summary — SUMIFS Rollup with Margin % and YoY Growth
A3: Month | B3: Units Sold | C3: Revenue (₹) | D3: COGS (₹) | E3: Gross Profit (₹) | F3: Gross Margin % | G3: Revenue YoY % | H3: 3-Mo Avg Revenue (₹)
A4: Jan-2024 | B4: =SUMIF('Sales Data'!$B$4:$B$291,$A4,'Sales Data'!$E$4:$E$291) -> 3623 | C4: =SUMIF('Sales Data'!$B$4:$B$291,$A4,'Sales Data'!$G$4:$G$291) -> 14716127 | D4: =SUMIF('Sales Data'!$B$4:$B$291,$A4,'Sales Data'!$I$4:$I$291) -> 6915750.5 | E4: =C4-D4 -> 7800376.6 | F4: =IF(C4=0,"-",E4/C4) -> 0.53005635 | G4: n/a | H4: n/a
A5: Feb-2024 | B5: =SUMIF('Sales Data'!$B$4:$B$291,$A5,'Sales Data'!$E$4:$E$291) -> 3598 | C5: =SUMIF('Sales Data'!$B$4:$B$291,$A5,'Sales Data'!$G$4:$G$291) -> 14687445 | D5: =SUMIF('Sales Data'!$B$4:$B$291,$A5,'Sales Data'!$I$4:$I$291) -> 6885321.5 | E5: =C5-D5 -> 7802123.7 | F5: =IF(C5=0,"-",E5/C5) -> 0.5312104 | G5: n/a | H5: n/a
A6: Mar-2024 | B6: =SUMIF('Sales Data'!$B$4:$B$291,$A6,'Sales Data'!$E$4:$E$291) -> 4134 | C6: =SUMIF('Sales Data'!$B$4:$B$291,$A6,'Sales Data'!$G$4:$G$291) -> 16988766 | D6: =SUMIF('Sales Data'!$B$4:$B$291,$A6,'Sales Data'!$I$4:$I$291) -> 7961953.5 | E6: =C6-D6 -> 9026812.4 | F6: =IF(C6=0,"-",E6/C6) -> 0.53134009 | G6: n/a | H6: =AVERAGE(C4:C6) -> 15464113
A7: Apr-2024 | B7: =SUMIF('Sales Data'!$B$4:$B$291,$A7,'Sales Data'!$E$4:$E$291) -> 4424 | C7: =SUMIF('Sales Data'!$B$4:$B$291,$A7,'Sales Data'!$G$4:$G$291) -> 18260181 | D7: =SUMIF('Sales Data'!$B$4:$B$291,$A7,'Sales Data'!$I$4:$I$291) -> 8601815 | E7: =C7-D7 -> 9658365.9 | F7: =IF(C7=0,"-",E7/C7) -> 0.52893046 | G7: n/a | H7: =AVERAGE(C5:C7) -> 16645464
A8: May-2024 | B8: =SUMIF('Sales Data'!$B$4:$B$291,$A8,'Sales Data'!$E$4:$E$291) -> 4779 | C8: =SUMIF('Sales Data'!$B$4:$B$291,$A8,'Sales Data'!$G$4:$G$291) -> 20020429 | D8: =SUMIF('Sales Data'!$B$4:$B$291,$A8,'Sales Data'!$I$4:$I$291) -> 9424080.4 | E8: =C8-D8 -> 10596349 | F8: =IF(C8=0,"-",E8/C8) -> 0.5292768 | G8: n/a | H8: =AVERAGE(C6:C8) -> 18423125
A9: Jun-2024 | B9: =SUMIF('Sales Data'!$B$4:$B$291,$A9,'Sales Data'!$E$4:$E$291) -> 4914 | C9: =SUMIF('Sales Data'!$B$4:$B$291,$A9,'Sales Data'!$G$4:$G$291) -> 20637440 | D9: =SUMIF('Sales Data'!$B$4:$B$291,$A9,'Sales Data'!$I$4:$I$291) -> 9719268.2 | E9: =C9-D9 -> 10918172 | F9: =IF(C9=0,"-",E9/C9) -> 0.52904681 | G9: n/a | H9: =AVERAGE(C7:C9) -> 19639350
A10: Jul-2024 | B10: =SUMIF('Sales Data'!$B$4:$B$291,$A10,'Sales Data'!$E$4:$E$291) -> 4806 | C10: =SUMIF('Sales Data'!$B$4:$B$291,$A10,'Sales Data'!$G$4:$G$291) -> 19973820 | D10: =SUMIF('Sales Data'!$B$4:$B$291,$A10,'Sales Data'!$I$4:$I$291) -> 9400897.7 | E10: =C10-D10 -> 10572922 | F10: =IF(C10=0,"-",E10/C10) -> 0.52933902 | G10: n/a | H10: =AVERAGE(C8:C10) -> 20210563
A11: Aug-2024 | B11: =SUMIF('Sales Data'!$B$4:$B$291,$A11,'Sales Data'!$E$4:$E$291) -> 4791 | C11: =SUMIF('Sales Data'!$B$4:$B$291,$A11,'Sales Data'!$G$4:$G$291) -> 19598397 | D11: =SUMIF('Sales Data'!$B$4:$B$291,$A11,'Sales Data'!$I$4:$I$291) -> 9207521.8 | E11: =C11-D11 -> 10390875 | F11: =IF(C11=0,"-",E11/C11) -> 0.53019005 | G11: n/a | H11: =AVERAGE(C9:C11) -> 20069885
A12: Sep-2024 | B12: =SUMIF('Sales Data'!$B$4:$B$291,$A12,'Sales Data'!$E$4:$E$291) -> 4765 | C12: =SUMIF('Sales Data'!$B$4:$B$291,$A12,'Sales Data'!$G$4:$G$291) -> 19680424 | D12: =SUMIF('Sales Data'!$B$4:$B$291,$A12,'Sales Data'!$I$4:$I$291) -> 9229207.3 | E12: =C12-D12 -> 10451216 | F12: =IF(C12=0,"-",E12/C12) -> 0.53104631 | G12: n/a | H12: =AVERAGE(C10:C12) -> 19750880
A13: Oct-2024 | B13: =SUMIF('Sales Data'!$B$4:$B$291,$A13,'Sales Data'!$E$4:$E$291) -> 5156 | C13: =SUMIF('Sales Data'!$B$4:$B$291,$A13,'Sales Data'!$G$4:$G$291) -> 20943316 | D13: =SUMIF('Sales Data'!$B$4:$B$291,$A13,'Sales Data'!$I$4:$I$291) -> 9783078.9 | E13: =C13-D13 -> 11160237 | F13: =IF(C13=0,"-",E13/C13) -> 0.53287823 | G13: n/a | H13: =AVERAGE(C11:C13) -> 20074045
A14: Nov-2024 | B14: =SUMIF('Sales Data'!$B$4:$B$291,$A14,'Sales Data'!$E$4:$E$291) -> 6061 | C14: =SUMIF('Sales Data'!$B$4:$B$291,$A14,'Sales Data'!$G$4:$G$291) -> 25744746 | D14: =SUMIF('Sales Data'!$B$4:$B$291,$A14,'Sales Data'!$I$4:$I$291) -> 12166721 | E14: =C14-D14 -> 13578025 | F14: =IF(C14=0,"-",E14/C14) -> 0.52740956 | G14: n/a | H14: =AVERAGE(C12:C14) -> 22122829
A15: Dec-2024 | B15: =SUMIF('Sales Data'!$B$4:$B$291,$A15,'Sales Data'!$E$4:$E$291) -> 7163 | C15: =SUMIF('Sales Data'!$B$4:$B$291,$A15,'Sales Data'!$G$4:$G$291) -> 29473009 | D15: =SUMIF('Sales Data'!$B$4:$B$291,$A15,'Sales Data'!$I$4:$I$291) -> 13853068 | E15: =C15-D15 -> 15619941 | F15: =IF(C15=0,"-",E15/C15) -> 0.52997442 | G15: n/a | H15: =AVERAGE(C13:C15) -> 25387024
A16: Jan-2025 | B16: =SUMIF('Sales Data'!$B$4:$B$291,$A16,'Sales Data'!$E$4:$E$291) -> 4208 | C16: =SUMIF('Sales Data'!$B$4:$B$291,$A16,'Sales Data'!$G$4:$G$291) -> 17380627 | D16: =SUMIF('Sales Data'!$B$4:$B$291,$A16,'Sales Data'!$I$4:$I$291) -> 8167772.7 | E16: =C16-D16 -> 9212854.4 | F16: =IF(C16=0,"-",E16/C16) -> 0.53006456 | G16: =IF(C4=0,"-",(C16-C4)/C4) -> 0.18105987 | H16: =AVERAGE(C14:C16) -> 24199461
A17: Feb-2025 | B17: =SUMIF('Sales Data'!$B$4:$B$291,$A17,'Sales Data'!$E$4:$E$291) -> 4118 | C17: =SUMIF('Sales Data'!$B$4:$B$291,$A17,'Sales Data'!$G$4:$G$291) -> 17119732 | D17: =SUMIF('Sales Data'!$B$4:$B$291,$A17,'Sales Data'!$I$4:$I$291) -> 8037895.8 | E17: =C17-D17 -> 9081836.6 | F17: =IF(C17=0,"-",E17/C17) -> 0.5304894 | G17: =IF(C5=0,"-",(C17-C5)/C5) -> 0.16560315 | H17: =AVERAGE(C15:C17) -> 21324456
A18: Mar-2025 | B18: =SUMIF('Sales Data'!$B$4:$B$291,$A18,'Sales Data'!$E$4:$E$291) -> 4909 | C18: =SUMIF('Sales Data'!$B$4:$B$291,$A18,'Sales Data'!$G$4:$G$291) -> 20025058 | D18: =SUMIF('Sales Data'!$B$4:$B$291,$A18,'Sales Data'!$I$4:$I$291) -> 9408785.4 | E18: =C18-D18 -> 10616272 | F18: =IF(C18=0,"-",E18/C18) -> 0.5301494 | G18: =IF(C6=0,"-",(C18-C6)/C6) -> 0.1787235 | H18: =AVERAGE(C16:C18) -> 18175139
A19: Apr-2025 | B19: =SUMIF('Sales Data'!$B$4:$B$291,$A19,'Sales Data'!$E$4:$E$291) -> 5080 | C19: =SUMIF('Sales Data'!$B$4:$B$291,$A19,'Sales Data'!$G$4:$G$291) -> 20876730 | D19: =SUMIF('Sales Data'!$B$4:$B$291,$A19,'Sales Data'!$I$4:$I$291) -> 9789590.4 | E19: =C19-D19 -> 11087139 | F19: =IF(C19=0,"-",E19/C19) -> 0.53107644 | G19: =IF(C7=0,"-",(C19-C7)/C7) -> 0.14329259 | H19: =AVERAGE(C17:C19) -> 19340507
A20: May-2025 | B20: =SUMIF('Sales Data'!$B$4:$B$291,$A20,'Sales Data'!$E$4:$E$291) -> 5380 | C20: =SUMIF('Sales Data'!$B$4:$B$291,$A20,'Sales Data'!$G$4:$G$291) -> 22158514 | D20: =SUMIF('Sales Data'!$B$4:$B$291,$A20,'Sales Data'!$I$4:$I$291) -> 10404974 | E20: =C20-D20 -> 11753540 | F20: =IF(C20=0,"-",E20/C20) -> 0.53042999 | G20: =IF(C8=0,"-",(C20-C8)/C8) -> 0.10679514 | H20: =AVERAGE(C18:C20) -> 21020100
A21: Jun-2025 | B21: =SUMIF('Sales Data'!$B$4:$B$291,$A21,'Sales Data'!$E$4:$E$291) -> 5745 | C21: =SUMIF('Sales Data'!$B$4:$B$291,$A21,'Sales Data'!$G$4:$G$291) -> 23465606 | D21: =SUMIF('Sales Data'!$B$4:$B$291,$A21,'Sales Data'!$I$4:$I$291) -> 11028681 | E21: =C21-D21 -> 12436925 | F21: =IF(C21=0,"-",E21/C21) -> 0.53000655 | G21: =IF(C9=0,"-",(C21-C9)/C9) -> 0.13704057 | H21: =AVERAGE(C19:C21) -> 22166950
A22: Jul-2025 | B22: =SUMIF('Sales Data'!$B$4:$B$291,$A22,'Sales Data'!$E$4:$E$291) -> 5798 | C22: =SUMIF('Sales Data'!$B$4:$B$291,$A22,'Sales Data'!$G$4:$G$291) -> 24174100 | D22: =SUMIF('Sales Data'!$B$4:$B$291,$A22,'Sales Data'!$I$4:$I$291) -> 11345634 | E22: =C22-D22 -> 12828466 | F22: =IF(C22=0,"-",E22/C22) -> 0.53066985 | G22: =IF(C10=0,"-",(C22-C10)/C10) -> 0.21028927 | H22: =AVERAGE(C20:C22) -> 23266073
A23: Aug-2025 | B23: =SUMIF('Sales Data'!$B$4:$B$291,$A23,'Sales Data'!$E$4:$E$291) -> 5449 | C23: =SUMIF('Sales Data'!$B$4:$B$291,$A23,'Sales Data'!$G$4:$G$291) -> 22402619 | D23: =SUMIF('Sales Data'!$B$4:$B$291,$A23,'Sales Data'!$I$4:$I$291) -> 10525793 | E23: =C23-D23 -> 11876825 | F23: =IF(C23=0,"-",E23/C23) -> 0.53015344 | G23: =IF(C11=0,"-",(C23-C11)/C11) -> 0.14308426 | H23: =AVERAGE(C21:C23) -> 23347442
A24: Sep-2025 | B24: =SUMIF('Sales Data'!$B$4:$B$291,$A24,'Sales Data'!$E$4:$E$291) -> 5350 | C24: =SUMIF('Sales Data'!$B$4:$B$291,$A24,'Sales Data'!$G$4:$G$291) -> 21789298 | D24: =SUMIF('Sales Data'!$B$4:$B$291,$A24,'Sales Data'!$I$4:$I$291) -> 10229187 | E24: =C24-D24 -> 11560111 | F24: =IF(C24=0,"-",E24/C24) -> 0.53054078 | G24: =IF(C12=0,"-",(C24-C12)/C12) -> 0.10715594 | H24: =AVERAGE(C22:C24) -> 22788672
A25: Oct-2025 | B25: =SUMIF('Sales Data'!$B$4:$B$291,$A25,'Sales Data'!$E$4:$E$291) -> 5936 | C25: =SUMIF('Sales Data'!$B$4:$B$291,$A25,'Sales Data'!$G$4:$G$291) -> 24102709 | D25: =SUMIF('Sales Data'!$B$4:$B$291,$A25,'Sales Data'!$I$4:$I$291) -> 11288092 | E25: =C25-D25 -> 12814616 | F25: =IF(C25=0,"-",E25/C25) -> 0.53166706 | G25: =IF(C13=0,"-",(C25-C13)/C13) -> 0.15085446 | H25: =AVERAGE(C23:C25) -> 22764875
A26: Nov-2025 | B26: =SUMIF('Sales Data'!$B$4:$B$291,$A26,'Sales Data'!$E$4:$E$291) -> 7228 | C26: =SUMIF('Sales Data'!$B$4:$B$291,$A26,'Sales Data'!$G$4:$G$291) -> 29293725 | D26: =SUMIF('Sales Data'!$B$4:$B$291,$A26,'Sales Data'!$I$4:$I$291) -> 13700214 | E26: =C26-D26 -> 15593511 | F26: =IF(C26=0,"-",E26/C26) -> 0.53231575 | G26: =IF(C14=0,"-",(C26-C14)/C14) -> 0.13785256 | H26: =AVERAGE(C24:C26) -> 25061911
A27: Dec-2025 | B27: =SUMIF('Sales Data'!$B$4:$B$291,$A27,'Sales Data'!$E$4:$E$291) -> 8157 | C27: =SUMIF('Sales Data'!$B$4:$B$291,$A27,'Sales Data'!$G$4:$G$291) -> 34177075 | D27: =SUMIF('Sales Data'!$B$4:$B$291,$A27,'Sales Data'!$I$4:$I$291) -> 16058639 | E27: =C27-D27 -> 18118436 | F27: =IF(C27=0,"-",E27/C27) -> 0.5301342 | G27: =IF(C15=0,"-",(C27-C15)/C15) -> 0.15960593 | H27: =AVERAGE(C25:C27) -> 29191170
A28: TOTAL / AVG | B28: =SUM(B4:B27) -> 125572 | C28: =SUM(C4:C27) -> 5.1768989e+08 | D28: =SUM(D4:D27) -> 2.4313394e+08 | E28: =SUM(E4:E27) -> 2.7455595e+08 | F28: =E28/C28 -> 0.53034829
A30: Region x Category — FY2025 Revenue
A32: Region | B32: Apparel | C32: Footwear | D32: Accessories | E32: Total
A33: North | B33: =SUMPRODUCT(('Sales Data'!$C$4:$C$291=$A33)*('Sales Data'!$D$4:$D$291=B$32)*(RIGHT('Sales Data'!$B$4:$B$291,4)="2025")*'Sales Data'!$G$4:$G$291) -> 27631403 | C33: =SUMPRODUCT(('Sales Data'!$C$4:$C$291=$A33)*('Sales Data'!$D$4:$D$291=C$32)*(RIGHT('Sales Data'!$B$4:$B$291,4)="2025")*'Sales Data'!$G$4:$G$291) -> 28837292 | D33: =SUMPRODUCT(('Sales Data'!$C$4:$C$291=$A33)*('Sales Data'!$D$4:$D$291=D$32)*(RIGHT('Sales Data'!$B$4:$B$291,4)="2025")*'Sales Data'!$G$4:$G$291) -> 13311182 | E33: =SUM(B33:D33) -> 69779877
A34: South | B34: =SUMPRODUCT(('Sales Data'!$C$4:$C$291=$A34)*('Sales Data'!$D$4:$D$291=B$32)*(RIGHT('Sales Data'!$B$4:$B$291,4)="2025")*'Sales Data'!$G$4:$G$291) -> 25238505 | C34: =SUMPRODUCT(('Sales Data'!$C$4:$C$291=$A34)*('Sales Data'!$D$4:$D$291=C$32)*(RIGHT('Sales Data'!$B$4:$B$291,4)="2025")*'Sales Data'!$G$4:$G$291) -> 25245704 | D34: =SUMPRODUCT(('Sales Data'!$C$4:$C$291=$A34)*('Sales Data'!$D$4:$D$291=D$32)*(RIGHT('Sales Data'!$B$4:$B$291,4)="2025")*'Sales Data'!$G$4:$G$291) -> 11877748 | E34: =SUM(B34:D34) -> 62361957
A35: East | B35: =SUMPRODUCT(('Sales Data'!$C$4:$C$291=$A35)*('Sales Data'!$D$4:$D$291=B$32)*(RIGHT('Sales Data'!$B$4:$B$291,4)="2025")*'Sales Data'!$G$4:$G$291) -> 31775707 | C35: =SUMPRODUCT(('Sales Data'!$C$4:$C$291=$A35)*('Sales Data'!$D$4:$D$291=C$32)*(RIGHT('Sales Data'!$B$4:$B$291,4)="2025")*'Sales Data'!$G$4:$G$291) -> 30183286 | D35: =SUMPRODUCT(('Sales Data'!$C$4:$C$291=$A35)*('Sales Data'!$D$4:$D$291=D$32)*(RIGHT('Sales Data'!$B$4:$B$291,4)="2025")*'Sales Data'!$G$4:$G$291) -> 14485468 | E35: =SUM(B35:D35) -> 76444461
A36: West | B36: =SUMPRODUCT(('Sales Data'!$C$4:$C$291=$A36)*('Sales Data'!$D$4:$D$291=B$32)*(RIGHT('Sales Data'!$B$4:$B$291,4)="2025")*'Sales Data'!$G$4:$G$291) -> 27860373 | C36: =SUMPRODUCT(('Sales Data'!$C$4:$C$291=$A36)*('Sales Data'!$D$4:$D$291=C$32)*(RIGHT('Sales Data'!$B$4:$B$291,4)="2025")*'Sales Data'!$G$4:$G$291) -> 28146418 | D36: =SUMPRODUCT(('Sales Data'!$C$4:$C$291=$A36)*('Sales Data'!$D$4:$D$291=D$32)*(RIGHT('Sales Data'!$B$4:$B$291,4)="2025")*'Sales Data'!$G$4:$G$291) -> 12372706 | E36: =SUM(B36:D36) -> 68379497
A37: Total | B37: =SUM(B33:B36) -> 1.1250599e+08 | C37: =SUM(C33:C36) -> 1.124127e+08 | D37: =SUM(D33:D36) -> 52047104 | E37: =SUM(E33:E36) -> 2.7696579e+08

Sheet Assumptions
A1: Forecast Assumptions
A2: Edit the blue cells to drive the 12-month forecast
A3: Revenue Drivers
A4: Base month revenue (last actual, Dec-2025) | B4: ='Monthly Summary'!C27 -> 34177075 | C4: Linked from Monthly Summary
A5: Monthly revenue growth rate | B5: 0.02 | C5: Applied compounding month over month
A6: Seasonality uplift — Nov/Dec (holiday) | B6: 0.15 | C6: Extra growth applied in Nov & Dec
A8: Margin & Cost Drivers
A9: Blended COGS % of revenue | B9: 0.455 | C9: Weighted avg of category COGS rates
A10: Operating expenses % of revenue | B10: 0.28 | C10: Marketing, fulfillment, G&A combined
A11: D&A % of revenue | B11: 0.02
A12: Interest expense (₹/mo) | B12: 764000 | C12: Fixed debt service
A13: Effective tax rate | B13: 0.24
A15: Forecast Window
A16: Forecast start month | B16: Jan-2026 | C16: First forward-looking month
A17: Forecast length (months) | B17: 12

Sheet Financial Model
A1: 12-Month Forward Income Statement
A2: Fully driven by Assumptions sheet — change inputs there to flex this model
A3: Line Item (₹) | B3: Jan-2026 | C3: Feb-2026 | D3: Mar-2026 | E3: Apr-2026 | F3: May-2026 | G3: Jun-2026 | H3: Jul-2026 | I3: Aug-2026 | J3: Sep-2026 | K3: Oct-2026 | L3: Nov-2026 | M3: Dec-2026 | N3: FY2026 Total
A4: Revenue | B4: =Assumptions!$B$4*(1+Assumptions!$B$5) -> 34860617 | C4: =B4*(1+Assumptions!$B$5) -> 35557829 | D4: =C4*(1+Assumptions!$B$5) -> 36268986 | E4: =D4*(1+Assumptions!$B$5) -> 36994366 | F4: =E4*(1+Assumptions!$B$5) -> 37734253 | G4: =F4*(1+Assumptions!$B$5) -> 38488938 | H4: =G4*(1+Assumptions!$B$5) -> 39258717 | I4: =H4*(1+Assumptions!$B$5) -> 40043891 | J4: =I4*(1+Assumptions!$B$5) -> 40844769 | K4: =J4*(1+Assumptions!$B$5) -> 41661664 | L4: =K4*(1+Assumptions!$B$5)*(1+Assumptions!$B$6) -> 48869132 | M4: =L4*(1+Assumptions!$B$5)*(1+Assumptions!$B$6) -> 57323492 | N4: =SUM(B4:M4) -> 4.8790665e+08
A5: COGS | B5: =B4*Assumptions!$B$9 -> 15861581 | C5: =C4*Assumptions!$B$9 -> 16178812 | D5: =D4*Assumptions!$B$9 -> 16502389 | E5: =E4*Assumptions!$B$9 -> 16832436 | F5: =F4*Assumptions!$B$9 -> 17169085 | G5: =G4*Assumptions!$B$9 -> 17512467 | H5: =H4*Assumptions!$B$9 -> 17862716 | I5: =I4*Assumptions!$B$9 -> 18219970 | ... M5: =M4*Assumptions!$B$9 -> 26082189 | N5: =SUM(B5:M5) -> 2.2199753e+08
A6: Gross Profit | B6: =B4-B5 -> 18999036 | C6: =C4-C5 -> 19379017 | D6: =D4-D5 -> 19766597 | E6: =E4-E5 -> 20161929 | F6: =F4-F5 -> 20565168 | G6: =G4-G5 -> 20976471 | H6: =H4-H5 -> 21396001 | I6: =I4-I5 -> 21823921 | ... M6: =M4-M5 -> 31241303 | N6: =SUM(B6:M6) -> 2.6590913e+08
A7: Gross Margin % | B7: =B6/B4 -> 0.545 | C7: =C6/C4 -> 0.545 | D7: =D6/D4 -> 0.545 | E7: =E6/E4 -> 0.545 | F7: =F6/F4 -> 0.545 | G7: =G6/G4 -> 0.545 | H7: =H6/H4 -> 0.545 | I7: =I6/I4 -> 0.545 | ... N7: =N6/N4 -> 0.545
A8: Operating Expenses | B8: =B4*Assumptions!$B$10 -> 9760972.7 | C8: =C4*Assumptions!$B$10 -> 9956192.2 | D8: =D4*Assumptions!$B$10 -> 10155316 | E8: =E4*Assumptions!$B$10 -> 10358422 | F8: =F4*Assumptions!$B$10 -> 10565591 | G8: =G4*Assumptions!$B$10 -> 10776903 | H8: =H4*Assumptions!$B$10 -> 10992441 | I8: =I4*Assumptions!$B$10 -> 11212289 | ... M8: =M4*Assumptions!$B$10 -> 16050578 | N8: =SUM(B8:M8) -> 1.3661386e+08
A9: EBITDA | B9: =B6-B8 -> 9238063.5 | C9: =C6-C8 -> 9422824.7 | D9: =D6-D8 -> 9611281.2 | E9: =E6-E8 -> 9803506.9 | F9: =F6-F8 -> 9999577 | G9: =G6-G8 -> 10199569 | H9: =H6-H8 -> 10403560 | I9: =I6-I8 -> 10611631 | ... M9: =M6-M8 -> 15190725 | N9: =SUM(B9:M9) -> 1.2929526e+08
A10: D&A | B10: =B4*Assumptions!$B$11 -> 697212.34 | C10: =C4*Assumptions!$B$11 -> 711156.58 | D10: =D4*Assumptions!$B$11 -> 725379.72 | E10: =E4*Assumptions!$B$11 -> 739887.31 | F10: =F4*Assumptions!$B$11 -> 754685.06 | G10: =G4*Assumptions!$B$11 -> 769778.76 | H10: =H4*Assumptions!$B$11 -> 785174.33 | I10: =I4*Assumptions!$B$11 -> 800877.82 | ... M10: =M4*Assumptions!$B$11 -> 1146469.8 | N10: =SUM(B10:M10) -> 9758133.1
A11: EBIT | B11: =B9-B10 -> 8540851.1 | C11: =C9-C10 -> 8711668.2 | D11: =D9-D10 -> 8885901.5 | E11: =E9-E10 -> 9063619.6 | F11: =F9-F10 -> 9244891.9 | G11: =G9-G10 -> 9429789.8 | H11: =H9-H10 -> 9618385.6 | I11: =I9-I10 -> 9810753.3 | ... M11: =M9-M10 -> 14044256 | N11: =SUM(B11:M11) -> 1.1953713e+08
A12: Interest Expense | B12: =Assumptions!$B$12 -> 764000 | C12: =Assumptions!$B$12 -> 764000 | D12: =Assumptions!$B$12 -> 764000 | E12: =Assumptions!$B$12 -> 764000 | F12: =Assumptions!$B$12 -> 764000 | G12: =Assumptions!$B$12 -> 764000 | H12: =Assumptions!$B$12 -> 764000 | I12: =Assumptions!$B$12 -> 764000 | ... M12: =Assumptions!$B$12 -> 764000 | N12: =SUM(B12:M12) -> 9168000
A13: Pre-Tax Income (EBT) | B13: =B11-B12 -> 7776851.1 | C13: =C11-C12 -> 7947668.2 | D13: =D11-D12 -> 8121901.5 | E13: =E11-E12 -> 8299619.6 | F13: =F11-F12 -> 8480891.9 | G13: =G11-G12 -> 8665789.8 | H13: =H11-H12 -> 8854385.6 | I13: =I11-I12 -> 9046753.3 | ... M13: =M11-M12 -> 13280256 | N13: =SUM(B13:M13) -> 1.1036913e+08
A14: Income Tax | B14: =MAX(B13,0)*Assumptions!$B$13 -> 1866444.3 | C14: =MAX(C13,0)*Assumptions!$B$13 -> 1907440.4 | D14: =MAX(D13,0)*Assumptions!$B$13 -> 1949256.4 | E14: =MAX(E13,0)*Assumptions!$B$13 -> 1991908.7 | F14: =MAX(F13,0)*Assumptions!$B$13 -> 2035414.1 | G14: =MAX(G13,0)*Assumptions!$B$13 -> 2079789.5 | H14: =MAX(H13,0)*Assumptions!$B$13 -> 2125052.5 | I14: =MAX(I13,0)*Assumptions!$B$13 -> 2171220.8 | ... M14: =MAX(M13,0)*Assumptions!$B$13 -> 3187261.3 | N14: =SUM(B14:M14) -> 26488591
A15: Net Income | B15: =B13-B14 -> 5910406.9 | C15: =C13-C14 -> 6040227.8 | D15: =D13-D14 -> 6172645.2 | E15: =E13-E14 -> 6307710.9 | F15: =F13-F14 -> 6445477.9 | G15: =G13-G14 -> 6586000.2 | H15: =H13-H14 -> 6729333 | I15: =I13-I14 -> 6875532.5 | ... M15: =M13-M14 -> 10092994 | N15: =SUM(B15:M15) -> 83880539
A16: Net Margin % | B16: =B15/B4 -> 0.16954396 | C16: =C15/C4 -> 0.16987054 | D16: =D15/D4 -> 0.17019073 | E16: =E15/E4 -> 0.17050464 | F16: =F15/F4 -> 0.17081239 | G16: =G15/G4 -> 0.17111411 | H16: =H15/H4 -> 0.17140991 | I16: =I15/I4 -> 0.17169991 | ... N16: =N15/N4 -> 0.17191924
